backtester/__init__.py
backtester/constants.py
backtester/feature_manager.py
backtester/financial_fn.py
backtester/instrument_data_manager.py
backtester/instruments_lookback_data.py
backtester/instruments_manager.py
backtester/logger.py
backtester/lookback_data.py
backtester/model_learning_system.py
backtester/model_learning_system_parameters.py
backtester/plotter.py
backtester/process_result.py
backtester/state_writer.py
backtester/trading_system.py
backtester/trading_system_parameters.py
backtester/version.py
backtester/versions.py
backtester/dataSource/__init__.py
backtester/dataSource/auquan_data_source.py
backtester/dataSource/csv_data_source.py
backtester/dataSource/data_source.py
backtester/dataSource/data_source_utils.py
backtester/dataSource/logfile_data_source.py
backtester/dataSource/nse_data_source.py
backtester/dataSource/quandl_data_source.py
backtester/dataSource/yahoo_data_source.py
backtester/executionSystem/QQ_execution_system.py
backtester/executionSystem/__init__.py
backtester/executionSystem/base_execution_system.py
backtester/executionSystem/basis_execution_system.py
backtester/executionSystem/pair_execution_system.py
backtester/executionSystem/simple_execution_system.py
backtester/executionSystem/simple_execution_system_fairvalue.py
backtester/features/__init__.py
backtester/features/argmax_feature.py
backtester/features/argmin_feature.py
backtester/features/bollinger_bands_feature.py
backtester/features/bollinger_bands_lower_feature.py
backtester/features/bollinger_bands_upper_feature.py
backtester/features/capital_feature.py
backtester/features/count_loss_feature.py
backtester/features/count_profit_feature.py
backtester/features/crossInstrument_correlation_feature.py
backtester/features/crossSectionMomentum_feature.py
backtester/features/delay_feature.py
backtester/features/difference_feature.py
backtester/features/direction_feature.py
backtester/features/exp_moving_average_feature.py
backtester/features/feature.py
auquan_toolbox-2.1.92.dist-info/LICENSE
auquan_toolbox-2.1.92.dist-info/METADATA
auquan_toolbox-2.1.92.dist-info/WHEEL
auquan_toolbox-2.1.92.dist-info/top_level.txt
auquan_toolbox-2.1.92.dist-info/RECORD
