Metadata-Version: 2.1
Name: auquan-toolbox
Version: 2.1.92
Summary: Auquan Toolbox for developing strategies and backtesting
Home-page: https://auquan.com
Author: Auquan Team
Author-email: info@auquan.com
License: MIT
Requires-Dist: requests
Requires-Dist: plotly
Requires-Dist: numpy
Requires-Dist: pandas
Requires-Dist: bs4
Requires-Dist: scipy
Requires-Dist: sklearn
Requires-Dist: lxml
Requires-Dist: tensorboard
Requires-Dist: tensorboardX
